odoo/addons/sale_order_action_invoice_create_hook/README.rst
odoo/addons/sale_order_action_invoice_create_hook/__init__.py
odoo/addons/sale_order_action_invoice_create_hook/__manifest__.py
odoo/addons/sale_order_action_invoice_create_hook/i18n/ca.po
odoo/addons/sale_order_action_invoice_create_hook/i18n/ca_ES.po
odoo/addons/sale_order_action_invoice_create_hook/i18n/de.po
odoo/addons/sale_order_action_invoice_create_hook/i18n/el_GR.po
odoo/addons/sale_order_action_invoice_create_hook/i18n/es.po
odoo/addons/sale_order_action_invoice_create_hook/i18n/es_VE.po
odoo/addons/sale_order_action_invoice_create_hook/i18n/fi.po
odoo/addons/sale_order_action_invoice_create_hook/i18n/fr.po
odoo/addons/sale_order_action_invoice_create_hook/i18n/hr.po
odoo/addons/sale_order_action_invoice_create_hook/i18n/hu.po
odoo/addons/sale_order_action_invoice_create_hook/i18n/it.po
odoo/addons/sale_order_action_invoice_create_hook/i18n/nl.po
odoo/addons/sale_order_action_invoice_create_hook/i18n/pt_BR.po
odoo/addons/sale_order_action_invoice_create_hook/i18n/ro.po
odoo/addons/sale_order_action_invoice_create_hook/i18n/sale_order_action_invoice_create_hook.pot
odoo/addons/sale_order_action_invoice_create_hook/i18n/sl.po
odoo/addons/sale_order_action_invoice_create_hook/i18n/sl_SI.po
odoo/addons/sale_order_action_invoice_create_hook/i18n/tr.po
odoo/addons/sale_order_action_invoice_create_hook/i18n/vi_VN.po
odoo/addons/sale_order_action_invoice_create_hook/i18n/zh_CN.po
odoo/addons/sale_order_action_invoice_create_hook/model/__init__.py
odoo/addons/sale_order_action_invoice_create_hook/model/sale_order.py
odoo/addons/sale_order_action_invoice_create_hook/readme/CONTRIBUTORS.rst
odoo/addons/sale_order_action_invoice_create_hook/readme/DESCRIPTION.rst
odoo/addons/sale_order_action_invoice_create_hook/readme/USAGE.rst
odoo/addons/sale_order_action_invoice_create_hook/static/description/icon.png
odoo/addons/sale_order_action_invoice_create_hook/static/description/index.html
odoo12_addon_sale_order_action_invoice_create_hook-12.0.1.0.3.dist-info/METADATA
odoo12_addon_sale_order_action_invoice_create_hook-12.0.1.0.3.dist-info/WHEEL
odoo12_addon_sale_order_action_invoice_create_hook-12.0.1.0.3.dist-info/top_level.txt
odoo12_addon_sale_order_action_invoice_create_hook-12.0.1.0.3.dist-info/RECORD
