Metadata-Version: 2.1
Name: odoo12-addon-sale-order-action-invoice-create-hook
Version: 12.0.1.0.3
Summary: Add more flexibility in the grouping parameters for the creation of invoices
Home-page: https://github.com/OCA/sale-workflow
Author: Eficent, Odoo Community Association (OCA)
Author-email: support@odoo-community.org
License: LGPL-3
Platform: UNKNOWN
Classifier: Programming Language :: Python
Classifier: Framework :: Odoo
Classifier: License :: OSI Approved :: GNU Lesser General Public License v3 (LGPLv3)
Requires-Python: >=3.5
Requires-Dist: odoo (<12.1dev,>=12.0a)
